iPLAN/__init__.py
iPLAN/main.py
iPLAN/observation_wrapper.py
iPLAN/run_ippo.py
iPLAN/components/__init__.py
iPLAN/components/action_selectors.py
iPLAN/components/episode_buffer.py
iPLAN/components/epsilon_schedules.py
iPLAN/components/transforms.py
iPLAN/utils/__init__.py
iPLAN/utils/dict2namedtuple.py
iPLAN/utils/logging.py
iPLAN/utils/rl_utils.py
iPLAN/utils/timehelper.py
iPLAN/utils/vis_utils.py
iPLAN/utils/mappo_utils/__init__.py
iPLAN/utils/mappo_utils/act.py
iPLAN/utils/mappo_utils/distributions.py
iPLAN/utils/mappo_utils/mlp.py
iPLAN/utils/mappo_utils/popart.py
iPLAN/utils/mappo_utils/rnn.py
iPLAN/utils/mappo_utils/separated_buffer.py
iPLAN/utils/mappo_utils/util.py
iPLAN/utils/mappo_utils/valuenorm.py
iPLAN-0.1.3.dist-info/LICENSE
iPLAN-0.1.3.dist-info/METADATA
iPLAN-0.1.3.dist-info/WHEEL
iPLAN-0.1.3.dist-info/top_level.txt
iPLAN-0.1.3.dist-info/RECORD
