Metadata-Version: 2.1
Name: iPLAN
Version: 0.1.3
Summary: Codebase for iPLAN: Intent-Aware Planning in Heterogeneous Traffic via Distributed Multi-Agent Reinforcement Learning
Home-page: https://github.com/wuxiyang1996/iPLAN
Author: Xiyang Wu
Author-email: wuxiyang1996@gmail.com
Classifier: Programming Language :: Python :: 3
Classifier: License :: OSI Approved :: MIT License
Classifier: Operating System :: OS Independent
License-File: LICENSE
